ndbounds/__init__.py
ndbounds/_api.py
ndbounds/_bounds.py
ndbounds/_conversion.py
ndbounds/_iou.py
ndbounds/_utils.py
ndbounds/_formats/__init__.py
ndbounds/_formats/base.py
ndbounds/_formats/format_cw.py
ndbounds/_formats/format_ecw.py
ndbounds/_formats/format_scw.py
ndbounds/_formats/format_se.py
ndbounds/_formats/format_sec.py
ndbounds/_formats/format_secw.py
ndbounds/_formats/format_sew.py
ndbounds/_formats/format_sw.py
ndbounds-4.0.5.dist-info/LICENSE
ndbounds-4.0.5.dist-info/METADATA
ndbounds-4.0.5.dist-info/WHEEL
ndbounds-4.0.5.dist-info/top_level.txt
ndbounds-4.0.5.dist-info/RECORD
