Metadata-Version: 2.1
Name: ndbounds
Version: 4.0.5
Summary: Toolbox for handling n-dimensional bounds
Author: Matthias Nadig
Author-email: nadig_develop@yahoo.com
License: MIT
Requires-Python: >=3.4
License-File: LICENSE
Requires-Dist: numpy
